{"c":["app/layout","webpack"],"r":["/_error","reactPlayerYouTube","reactPlayerSoundCloud","reactPlayerVimeo","reactPlayerFacebook","reactPlayerStreamable","reactPlayerWistia","reactPlayerTwitch","reactPlayerDailyMotion","reactPlayerMixcloud","reactPlayerVidyard","reactPlayerKaltura","reactPlayerFilePlayer","reactPlayerPreview"],"m":[null,"(app-pages-browser)/./app/globals.css","(app-pages-browser)/./components/CustomButton/FloatingButton.css","(app-pages-browser)/./components/CustomButton/FloatingButton.js","(app-pages-browser)/./components/CustomButton/MessengerChatButton.css","(app-pages-browser)/./components/CustomButton/MessengerChatButton.js","(app-pages-browser)/./components/popup/BlogPopup.js","(app-pages-browser)/./components/popup/ModalLayout.js","(app-pages-browser)/./components/popup/Popup.js","(app-pages-browser)/./components/popup/PortfolioPopup.js","(app-pages-browser)/./components/popup/ServicePopup.js","(app-pages-browser)/./components/popup/VideoPopup.js","(app-pages-browser)/./node_modules/deepmerge/dist/cjs.js","(app-pages-browser)/./node_modules/load-script/index.js","(app-pages-browser)/./node_modules/memoize-one/dist/memoize-one.esm.js","(app-pages-browser)/./node_modules/next/dist/build/polyfills/object-assign.js","(app-pages-browser)/./node_modules/next/dist/build/webpack/loaders/next-flight-client-entry-loader.js?modules=C%3A%5CUsers%5Csohan%5CDownloads%5Ciknow-personal-portfolio-react-nextjs-template-2024-01-30-07-26-40-utc%5Cpackage%5Ciknow%5Ccomponents%5Cpopup%5CPopup.js&modules=C%3A%5CUsers%5Csohan%5CDownloads%5Ciknow-personal-portfolio-react-nextjs-template-2024-01-30-07-26-40-utc%5Cpackage%5Ciknow%5Ccontext%5Ccontext.js&modules=C%3A%5CUsers%5Csohan%5CDownloads%5Ciknow-personal-portfolio-react-nextjs-template-2024-01-30-07-26-40-utc%5Cpackage%5Ciknow%5Ccomponents%5CCustomButton%5CFloatingButton.js&modules=C%3A%5CUsers%5Csohan%5CDownloads%5Ciknow-personal-portfolio-react-nextjs-template-2024-01-30-07-26-40-utc%5Cpackage%5Ciknow%5Ccomponents%5CCustomButton%5CMessengerChatButton.js&modules=C%3A%5CUsers%5Csohan%5CDownloads%5Ciknow-personal-portfolio-react-nextjs-template-2024-01-30-07-26-40-utc%5Cpackage%5Ciknow%5Cnode_modules%5Cnext%5Cfont%5Cgoogle%5Ctarget.css%3F%7B%22path%22%3A%22app%5C%5Clayout.js%22%2C%22import%22%3A%22Mulish%22%2C%22arguments%22%3A%5B%7B%22subsets%22%3A%5B%22latin%22%5D%2C%22weight%22%3A%5B%22200%22%2C%22300%22%2C%22400%22%2C%22500%22%2C%22600%22%2C%22700%22%2C%22800%22%2C%22900%22%5D%2C%22variable%22%3A%22--font-mulish%22%2C%22display%22%3A%22swap%22%7D%5D%2C%22variableName%22%3A%22mulish%22%7D&modules=C%3A%5CUsers%5Csohan%5CDownloads%5Ciknow-personal-portfolio-react-nextjs-template-2024-01-30-07-26-40-utc%5Cpackage%5Ciknow%5Cnode_modules%5Cnext%5Cfont%5Cgoogle%5Ctarget.css%3F%7B%22path%22%3A%22app%5C%5Clayout.js%22%2C%22import%22%3A%22Poppins%22%2C%22arguments%22%3A%5B%7B%22subsets%22%3A%5B%22latin%22%5D%2C%22weight%22%3A%5B%22300%22%2C%22400%22%2C%22500%22%2C%22600%22%2C%22700%22%2C%22800%22%2C%22900%22%5D%2C%22variable%22%3A%22--font-poppins%22%2C%22display%22%3A%22swap%22%7D%5D%2C%22variableName%22%3A%22poppins%22%7D&modules=C%3A%5CUsers%5Csohan%5CDownloads%5Ciknow-personal-portfolio-react-nextjs-template-2024-01-30-07-26-40-utc%5Cpackage%5Ciknow%5Cnode_modules%5Cnext%5Cfont%5Cgoogle%5Ctarget.css%3F%7B%22path%22%3A%22app%5C%5Clayout.js%22%2C%22import%22%3A%22Montserrat%22%2C%22arguments%22%3A%5B%7B%22subsets%22%3A%5B%22latin%22%5D%2C%22weight%22%3A%5B%22200%22%2C%22300%22%2C%22400%22%2C%22500%22%2C%22600%22%2C%22700%22%2C%22800%22%2C%22900%22%5D%2C%22variable%22%3A%22--font-montserrat%22%2C%22display%22%3A%22swap%22%7D%5D%2C%22variableName%22%3A%22montserrat%22%7D&modules=C%3A%5CUsers%5Csohan%5CDownloads%5Ciknow-personal-portfolio-react-nextjs-template-2024-01-30-07-26-40-utc%5Cpackage%5Ciknow%5Cpublic%5Ccss%5Cdark.css&modules=C%3A%5CUsers%5Csohan%5CDownloads%5Ciknow-personal-portfolio-react-nextjs-template-2024-01-30-07-26-40-utc%5Cpackage%5Ciknow%5Cpublic%5Ccss%5Cplugins.css&modules=C%3A%5CUsers%5Csohan%5CDownloads%5Ciknow-personal-portfolio-react-nextjs-template-2024-01-30-07-26-40-utc%5Cpackage%5Ciknow%5Cpublic%5Ccss%5Cstyle.css&modules=C%3A%5CUsers%5Csohan%5CDownloads%5Ciknow-personal-portfolio-react-nextjs-template-2024-01-30-07-26-40-utc%5Cpackage%5Ciknow%5Capp%5Cglobals.css&server=false!","(app-pages-browser)/./node_modules/next/dist/compiled/mini-css-extract-plugin/hmr/hotModuleReplacement.js","(app-pages-browser)/./node_modules/next/font/google/target.css?{\"path\":\"app\\\\layout.js\",\"import\":\"Montserrat\",\"arguments\":[{\"subsets\":[\"latin\"],\"weight\":[\"200\",\"300\",\"400\",\"500\",\"600\",\"700\",\"800\",\"900\"],\"variable\":\"--font-montserrat\",\"display\":\"swap\"}],\"variableName\":\"montserrat\"}","(app-pages-browser)/./node_modules/next/font/google/target.css?{\"path\":\"app\\\\layout.js\",\"import\":\"Mulish\",\"arguments\":[{\"subsets\":[\"latin\"],\"weight\":[\"200\",\"300\",\"400\",\"500\",\"600\",\"700\",\"800\",\"900\"],\"variable\":\"--font-mulish\",\"display\":\"swap\"}],\"variableName\":\"mulish\"}","(app-pages-browser)/./node_modules/next/font/google/target.css?{\"path\":\"app\\\\layout.js\",\"import\":\"Poppins\",\"arguments\":[{\"subsets\":[\"latin\"],\"weight\":[\"300\",\"400\",\"500\",\"600\",\"700\",\"800\",\"900\"],\"variable\":\"--font-poppins\",\"display\":\"swap\"}],\"variableName\":\"poppins\"}","(app-pages-browser)/./node_modules/prop-types/checkPropTypes.js","(app-pages-browser)/./node_modules/prop-types/factoryWithTypeCheckers.js","(app-pages-browser)/./node_modules/prop-types/index.js","(app-pages-browser)/./node_modules/prop-types/lib/ReactPropTypesSecret.js","(app-pages-browser)/./node_modules/prop-types/lib/has.js","(app-pages-browser)/./node_modules/react-fast-compare/index.js","(app-pages-browser)/./node_modules/react-is/cjs/react-is.development.js","(app-pages-browser)/./node_modules/react-is/index.js","(app-pages-browser)/./node_modules/react-player/lib/Player.js","(app-pages-browser)/./node_modules/react-player/lib/ReactPlayer.js","(app-pages-browser)/./node_modules/react-player/lib/index.js","(app-pages-browser)/./node_modules/react-player/lib/patterns.js","(app-pages-browser)/./node_modules/react-player/lib/players/index.js","(app-pages-browser)/./node_modules/react-player/lib/props.js","(app-pages-browser)/./node_modules/react-player/lib/utils.js","(app-pages-browser)/./public/css/dark.css","(app-pages-browser)/./public/css/plugins.css","(app-pages-browser)/./public/css/style.css","(app-pages-browser)/./utility/useClickOutside.js","./node_modules/next/dist/build/webpack/loaders/next-client-pages-loader.js?absolutePagePath=C%3A%5CUsers%5Csohan%5CDownloads%5Ciknow-personal-portfolio-react-nextjs-template-2024-01-30-07-26-40-utc%5Cpackage%5Ciknow%5Cnode_modules%5Cnext%5Cdist%5Cpages%5C_error.js&page=%2F_error!","(app-pages-browser)/./node_modules/react-player/lib/players/YouTube.js","(app-pages-browser)/./node_modules/react-player/lib/players/SoundCloud.js","(app-pages-browser)/./node_modules/react-player/lib/players/Vimeo.js","(app-pages-browser)/./node_modules/react-player/lib/players/Facebook.js","(app-pages-browser)/./node_modules/react-player/lib/players/Streamable.js","(app-pages-browser)/./node_modules/react-player/lib/players/Wistia.js","(app-pages-browser)/./node_modules/react-player/lib/players/Twitch.js","(app-pages-browser)/./node_modules/react-player/lib/players/DailyMotion.js","(app-pages-browser)/./node_modules/react-player/lib/players/Mixcloud.js","(app-pages-browser)/./node_modules/react-player/lib/players/Vidyard.js","(app-pages-browser)/./node_modules/react-player/lib/players/Kaltura.js","(app-pages-browser)/./node_modules/react-player/lib/players/FilePlayer.js","(app-pages-browser)/./node_modules/react-player/lib/Preview.js"]}